buildout.cfg
setup.py
src/zc/__init__.py
src/zc.monitorpdb.egg-info/PKG-INFO
src/zc.monitorpdb.egg-info/SOURCES.txt
src/zc.monitorpdb.egg-info/dependency_links.txt
src/zc.monitorpdb.egg-info/namespace_packages.txt
src/zc.monitorpdb.egg-info/not-zip-safe
src/zc.monitorpdb.egg-info/requires.txt
src/zc.monitorpdb.egg-info/top_level.txt
src/zc/monitorpdb/README.txt
src/zc/monitorpdb/__init__.py
src/zc/monitorpdb/configure.zcml
src/zc/monitorpdb/tests.py