Metadata-Version: 1.0
Name: zc.monitorpdb
Version: 1.0.0
Summary: zc.monitor plugin to debug running processes
Home-page: UNKNOWN
Author: Benji York
Author-email: benji@zope.com
License: ZPL 2.1
Platform: UNKNOWN
